log_report/__init__.py
log_report/__main__.py
log_report/resurses/__init__.py
log_report/resurses/log_worker.py
log_report-1.1.dist-info/METADATA
log_report-1.1.dist-info/WHEEL
log_report-1.1.dist-info/top_level.txt
log_report-1.1.dist-info/RECORD
