Metadata-Version: 2.1
Name: log-report
Version: 1.1
Summary: UNKNOWN
Home-page: UNKNOWN
Author: ME IS ME WHO ELSE
License: UNKNOWN
Platform: UNKNOWN
Requires-Dist: markdown
Requires-Dist: argparse
